emoji2lang/__init__.py
emoji2lang/converter.py
emoji2lang/data/zh_emoji_info.txt
emoji2lang-0.0.2.dist-info/METADATA
emoji2lang-0.0.2.dist-info/WHEEL
emoji2lang-0.0.2.dist-info/top_level.txt
emoji2lang-0.0.2.dist-info/RECORD
